iterm2/__init__.py
iterm2/_version.py
iterm2/alert.py
iterm2/api_pb2.py
iterm2/api_pb2.pyi
iterm2/app.py
iterm2/arrangement.py
iterm2/auth.py
iterm2/binding.py
iterm2/broadcast.py
iterm2/capabilities.py
iterm2/color.py
iterm2/colorpresets.py
iterm2/connection.py
iterm2/customcontrol.py
iterm2/filepanel.py
iterm2/focus.py
iterm2/keyboard.py
iterm2/lifecycle.py
iterm2/mainmenu.py
iterm2/notifications.py
iterm2/preferences.py
iterm2/profile.py
iterm2/prompt.py
iterm2/py.typed
iterm2/registration.py
iterm2/rpc.py
iterm2/screen.py
iterm2/selection.py
iterm2/session.py
iterm2/statusbar.py
iterm2/tab.py
iterm2/tmux.py
iterm2/tool.py
iterm2/transaction.py
iterm2/triggers.py
iterm2/util.py
iterm2/variables.py
iterm2/window.py
iterm2-2.13.dist-info/METADATA
iterm2-2.13.dist-info/WHEEL
iterm2-2.13.dist-info/top_level.txt
iterm2-2.13.dist-info/RECORD
