Metadata-Version: 2.1
Name: iterm2
Version: 2.13
Summary: Python interface to iTerm2's scripting API
Home-page: http://github.com/gnachman/iTerm2
Author: George Nachman
Author-email: gnachman@gmail.com
License: GPLv2
Platform: UNKNOWN
Classifier: Development Status :: 3 - Alpha
Classifier: License :: OSI Approved :: GNU General Public License v2 or later (GPLv2+)
Classifier: Programming Language :: Python :: 3.6
Requires-Dist: protobuf
Requires-Dist: websockets
Provides-Extra: full
Requires-Dist: pyobjc ; extra == 'full'
